armonia/__init__.py
armonia/colorfunctions.py
armonia/exceptions.py
armonia/py.typed
armonia/serialization.py
armonia/theme.py
armonia-1.1.1.dist-info/METADATA
armonia-1.1.1.dist-info/WHEEL
armonia-1.1.1.dist-info/licenses/LICENSE
armonia-1.1.1.dist-info/RECORD
