Metadata-Version: 2.4
Name: armonia
Version: 1.1.1
Summary: A Python library for theming facilities
Project-URL: Homepage, https://gitlab.com/Kencho1/armonia
Project-URL: Repository, https://gitlab.com/Kencho1/armonia.git
Project-URL: Issues, https://gitlab.com/Kencho1/armonia/-/issues
Author: Jesús Alonso Abad
License: MIT
License-File: LICENSE
Keywords: color-management,colors,polychromos,theme,theming
Classifier: Development Status :: 5 - Production/Stable
Classifier: Intended Audience :: Developers
Classifier: License :: OSI Approved :: MIT License
Classifier: Programming Language :: Python :: 3
Classifier: Programming Language :: Python :: 3.11
Classifier: Programming Language :: Python :: 3.12
Classifier: Programming Language :: Python :: 3.13
Classifier: Programming Language :: Python :: 3.14
Classifier: Topic :: Software Development :: Libraries :: Python Modules
Requires-Python: >=3.11
Requires-Dist: polychromos~=1.4
Provides-Extra: test
Requires-Dist: mypy>=1.0.0; extra == 'test'
Requires-Dist: pytest>=8.0.0; extra == 'test'
Requires-Dist: ruff>=0.6.0; extra == 'test'
Requires-Dist: tox>=4.0.0; extra == 'test'
